AUTHORS
LICENSE
MANIFEST.in
README.md
setup.py
pybfd3/__init__.py
pybfd3/bfd.c
pybfd3/bfd.py
pybfd3/bfd_base.py
pybfd3/bfd_headers.h
pybfd3/gen_supported_disasm.py
pybfd3/objdump.py
pybfd3/opcodes.c
pybfd3/opcodes.py
pybfd3/section.py
pybfd3/symbol.py
pybfd3/test_print_insn_i386.c
pybfd3.egg-info/PKG-INFO
pybfd3.egg-info/SOURCES.txt
pybfd3.egg-info/dependency_links.txt
pybfd3.egg-info/requires.txt
pybfd3.egg-info/top_level.txt