Metadata-Version: 2.1
Name: pybfd3
Version: 0.1.4
Summary: A Python (3.x compatible) interface to the GNU Binary File Descriptor (BFD) and opcodes library.
Home-page: https://github.com/b-2-r/pybfd3.git
Author: Groundworks Technologies OSS Team
Author-email: oss@groundworkstech.com
Maintainer: Manuel Gebele
Maintainer-email: m.gebele.contact@tuta.io
License: GPLv2
Platform: UNKNOWN
Classifier: Development Status :: 4 - Beta
Classifier: Intended Audience :: Developers
Classifier: Intended Audience :: Science/Research
Classifier: Intended Audience :: Other Audience
Classifier: License :: OSI Approved :: GNU General Public License v2 (GPLv2)
Classifier: Operating System :: MacOS
Classifier: Operating System :: POSIX
Classifier: Programming Language :: C
Classifier: Programming Language :: Assembly
Classifier: Programming Language :: Python :: 2
Classifier: Programming Language :: Python :: 3
Classifier: Topic :: Security
Classifier: Topic :: Software Development :: Disassemblers
Classifier: Topic :: Software Development :: Compilers
Classifier: Topic :: Software Development :: Debuggers
Classifier: Topic :: Software Development :: Embedded Systems
Classifier: Topic :: Software Development :: Libraries
Classifier: Topic :: Utilities
